lantern_data_manager/__init__.py
lantern_data_manager/dynamo/__init__.py
lantern_data_manager/dynamo/dynamodb.py
lantern_data_manager/elastic/__init__.py
lantern_data_manager/elastic/elastic_search.py
lantern_data_manager/influx/__init__.py
lantern_data_manager/influx/influx_controller.py
lantern_data_manager/timestream/__init__.py
lantern_data_manager/timestream/timestream_controller.py
lantern_data_manager/traccar/__init__.py
lantern_data_manager/traccar/api_controller.py
lantern_data_manager/traccar/exceptions.py
lantern_data_manager/traccar/traccar_controller.py
lantern_data_manager/utils/__init__.py
lantern_data_manager/utils/event.py
lantern_data_manager/utils/format.py
lantern_data_manager/utils/json.py
lantern_data_manager/utils/logger.py
lantern_data_manager/utils/query.py
lantern_data_manager/utils/request.py
lantern_data_manager/utils/setup.py
lantern_data_manager/utils/time.py
lantern_data_manager/utils/time_tmp.py
lantern_data_manager/utils/traccar.py
lantern_data_manager-1.0.27.dist-info/METADATA
lantern_data_manager-1.0.27.dist-info/WHEEL
lantern_data_manager-1.0.27.dist-info/top_level.txt
lantern_data_manager-1.0.27.dist-info/RECORD
