Metadata-Version: 2.1
Name: lantern-data-manager
Version: 1.0.27
Summary: Lantern Data Manager Library
Home-page: https://gitlab.com/lantern-tech/lantern-data-manager.git
Author: Lantern Technologies
Author-email: support@lantern.tech
License: BSD
Platform: any
Classifier: Development Status :: 5 - Production/Stable
Classifier: Environment :: Console
Classifier: Intended Audience :: Developers
Classifier: License :: OSI Approved :: BSD License
Classifier: Operating System :: POSIX
Classifier: Operating System :: MacOS
Classifier: Operating System :: Unix
Classifier: Operating System :: Microsoft :: Windows
Classifier: Programming Language :: Python :: 3
Classifier: Topic :: Software Development :: Libraries :: Python Modules
Requires-Dist: elasticsearch (==7.9.1)
Requires-Dist: PyJWT (==1.7.1)
Requires-Dist: influxdb-client (==1.14.0)
